preprocess.py
preprocess-2.0.0.dist-info/LICENSE.txt
preprocess-2.0.0.dist-info/METADATA
preprocess-2.0.0.dist-info/WHEEL
preprocess-2.0.0.dist-info/entry_points.txt
preprocess-2.0.0.dist-info/top_level.txt
preprocess-2.0.0.dist-info/RECORD
