Metadata-Version: 1.2
Name: preprocess
Version: 2.0.0
Summary: preprocess: a multi-language preprocessor
Home-page: http://github.com/doconce/preprocess/
Author: Trent Mick
Author-email: trentm@gmail.com
Maintainer: Kristian Gregorius Hustad
Maintainer-email: krihus@ifi.uio.no
License: http://www.opensource.org/licenses/mit-license.php
Platform: any
